{
    "key": "group_5a4ab7d13cd82",
    "title": "Tracked Gifts",
    "fields": [
        {
            "key": "field_5ab0515a41368",
            "label": "Product Image",
            "name": "product_image",
            "type": "image_select",
            "instructions": "",
            "required": 0,
            "conditional_logic": 0,
            "wrapper": {
                "width": "",
                "class": "",
                "id": ""
            },
            "choices": {
                "bouquet-1: Bouquet #1": "bouquet-1: Bouquet #1",
                "bouquet-2: Bouquet #2": "bouquet-2: Bouquet #2",
                "bouquet-3.": "Bouquet #3",
                "bouquet-4: Bouquet #4": "bouquet-4: Bouquet #4"
            },
            "default_value": [],
            "multiple": 0,
            "image_path": "\/app\/themes\/sage-theme\/resources\/images\/",
            "image_extension": "jpg"
        },
        {
            "key": "field_5aa5ac5d26fca",
            "label": "Story Meta",
            "name": "story_meta",
            "type": "text",
            "instructions": "",
            "required": 0,
            "conditional_logic": 0,
            "wrapper": {
                "width": "",
                "class": "",
                "id": ""
            },
            "default_value": "",
            "placeholder": "",
            "prepend": "",
            "append": "",
            "maxlength": ""
        },
        {
            "key": "field_5aa5ae42774ca",
            "label": "Story Title",
            "name": "story_title",
            "type": "text",
            "instructions": "",
            "required": 0,
            "conditional_logic": 0,
            "wrapper": {
                "width": "",
                "class": "",
                "id": ""
            },
            "default_value": "",
            "placeholder": "",
            "prepend": "",
            "append": "",
            "maxlength": ""
        }
    ],
    "location": [
        [
            {
                "param": "post_type",
                "operator": "==",
                "value": "tracked-gifts"
            }
        ]
    ],
    "menu_order": 0,
    "position": "normal",
    "style": "default",
    "label_placement": "top",
    "instruction_placement": "label",
    "hide_on_screen": "",
    "active": 1,
    "description": "",
    "modified": 1521504925
}